Workbook

Sheet DCF model
D1: 2017 | E1: =+D1+1 -> 2018 | F1: =+E1+1 -> 2019 | G1: =+F1+1 -> 2020 | H1: =+G1+1 -> 2021 | I1: =+H1+1 -> 2022 | J1: =+I1+1 -> 2023 | K1: =+J1+1 -> 2024 | L1: =+K1+1 -> 2025 | ... R1: =+Q1+1 -> 2031
B2: WALMART DCF model
A4: X | B4: Overview
B5: Company ticker | C5: WMT
B6: Date | C6: 46211
B7: Stock price | C7: 111.85
B8: Stock price forecast | C8: =R64 -> 155.73392
B9: Delta | C9: =C8/C7-1 -> 0.39234617
A11: X | B11: Assumptions
B13: Scenario | E13: 1. Pessimistic case | H13: 2. Base case | K13: 3. Optimistic case
B14: Case selected | C14: 3 | E14: Revenue g % | F14: 0.8 | K14: Revenue g % | L14: 1.2
B15: WACC | C15: =CHOOSE($C$14,F15,I15,L15) -> 0.065 | E15: WACC | F15: 0.08 | H15: WACC | I15: =WACC!C24 -> 0.069983139 | K15: WACC | L15: =6.5% -> 0.065
B16: TGR | C16: =CHOOSE($C$14,F16,I16,L16) -> 0.045 | E16: TGR | F16: 0.035 | H16: TGR | I16: 0.04 | K16: TGR | L16: 0.045
A18: X | B18: Income statement
B20: Revenue | D20: =IS!D10 -> 485.144 | E20: =IS!E10 -> 499.909 | F20: =IS!F10 -> 514.405 | G20: =IS!G10 -> 523.964 | H20: =IS!H10 -> 559.151 | I20: =IS!I10 -> 572.754 | J20: =IS!J10 -> 611.289 | K20: =IS!K10 -> 648.125 | ... M20: =IS!M10 -> 713.16 | N20: =M20*(1+N23) -> 749.7482 | O20: =N20*(1+O23) -> 793.79725 | P20: =O20*(1+P23) -> 840.94577 | Q20: =P20*(1+Q23) -> 892.74748 | R20: =Q20*(1+R23) -> 951.88453
B21: % growth | E21: =E20/D20-1 -> 0.030434263 | F21: =F20/E20-1 -> 0.028997278 | G21: =G20/F20-1 -> 0.018582634 | H21: =H20/G20-1 -> 0.067155377 | I21: =I20/H20-1 -> 0.024327954 | J21: =J20/I20-1 -> 0.067280194 | K21: =K20/J20-1 -> 0.06025955 | L21: =L20/K20-1 -> 0.050707811 | M21: =AVERAGE(H21:L21) -> 0.053946177 | N21: =CHOOSE($C$14,N22,N23,N24) -> 0.061565205 | O21: =CHOOSE($C$14,O22,O23,O24) -> 0.070502145 | P21: =CHOOSE($C$14,P22,P23,P24) -> 0.071275413 | Q21: =CHOOSE($C$14,Q22,Q23,Q24) -> 0.07391922 | R21: =CHOOSE($C$14,R22,R23,R24) -> 0.079489958
B22: Pessimistic case | N22: =$F$14*N23 -> 0.04104347 | O22: =$F$14*O23 -> 0.04700143 | P22: =$F$14*P23 -> 0.047516942 | Q22: =$F$14*Q23 -> 0.04927948 | R22: =$F$14*R23 -> 0.052993306
B23: Base case | N23: =AVERAGE(I21:M21) -> 0.051304337 | O23: =AVERAGE(J21:N21) -> 0.058751787 | P23: =AVERAGE(K21:O21) -> 0.059396177 | Q23: =AVERAGE(L21:P21) -> 0.06159935 | R23: =AVERAGE(M21:Q21) -> 0.066241632
B24: Optimistic case | N24: =$L$14*N23 -> 0.061565205 | O24: =$L$14*O23 -> 0.070502145 | P24: =$L$14*P23 -> 0.071275413 | Q24: =$L$14*Q23 -> 0.07391922 | R24: =$L$14*R23 -> 0.079489958
B26: EBIT | D26: =IS!D18 -> 22.035 | E26: =IS!E18 -> 21.203 | F26: =IS!F18 -> 21.957 | G26: =IS!G18 -> 21.468 | H26: =IS!H18 -> 26.948 | I26: =IS!I18 -> 28.442 | J26: =IS!J18 -> 24.528 | K26: =IS!K18 -> 27.012 | ... M26: =IS!M18 -> 29.83 | N26: =N20*N27 -> 32.855516 | O26: =O20*O27 -> 33.859276 | P26: =P20*P27 -> 36.295867 | Q26: =Q20*Q27 -> 38.796569 | R26: =R20*R27 -> 41.434763
B27: % sales | D27: =D26/D20 -> 0.045419504 | E27: =E26/E20 -> 0.042413719 | F27: =F26/F20 -> 0.042684266 | G27: =G26/G20 -> 0.040972281 | H27: =H26/H20 -> 0.048194495 | I27: =I26/I20 -> 0.049658318 | J27: =J26/J20 -> 0.040125047 | K27: =K26/K20 -> 0.041677146 | L27: =L26/L20 -> 0.043099018 | M27: =AVERAGE(H27:L27) -> 0.044550805 | N27: =AVERAGE(I27:M27) -> 0.043822067 | O27: =AVERAGE(J27:N27) -> 0.042654816 | P27: =AVERAGE(K27:O27) -> 0.04316077 | Q27: =AVERAGE(L27:P27) -> 0.043457495 | R27: =AVERAGE(M27:Q27) -> 0.043529191
B29: Taxes | D29: =IS!D37 -> 6.204 | E29: =IS!E37 -> 4.6 | F29: =IS!F37 -> 4.281 | G29: =IS!G37 -> 4.915 | H29: =IS!H37 -> 6.858 | I29: =IS!I37 -> 4.756 | J29: =IS!J37 -> 5.724 | K29: =IS!K37 -> 5.578 | ... M29: =IS!M37 -> 7.2 | N29: =N26*N30 -> 6.7738031 | O29: =O26*O30 -> 7.2445247 | P29: =P26*P30 -> 7.6249849 | Q29: =Q26*Q30 -> 8.17809 | R29: =R26*R30 -> 8.7445987
B30: % Tax rate | D30: =D29/D26 -> 0.28155208 | E30: =E29/E26 -> 0.21695043 | F30: =F29/F26 -> 0.19497199 | G30: =G29/G26 -> 0.22894541 | H30: =H29/H26 -> 0.25449013 | I30: =I29/I26 -> 0.1672175 | J30: =J29/J26 -> 0.23336595 | K30: =K29/K26 -> 0.20650081 | L30: =L29/L26 -> 0.20954003 | M30: =AVERAGE(H30:L30) -> 0.21422288 | N30: =AVERAGE(I30:M30) -> 0.20616944 | O30: =AVERAGE(J30:N30) -> 0.21395982 | P30: =AVERAGE(K30:O30) -> 0.2100786 | Q30: =AVERAGE(L30:P30) -> 0.21079416 | R30: =AVERAGE(M30:Q30) -> 0.21104498
B32: EBIAT (or NOPAT) | D32: =D26-D29 -> 15.831 | E32: =E26-E29 -> 16.603 | F32: =F26-F29 -> 17.676 | G32: =G26-G29 -> 16.553 | H32: =H26-H29 -> 20.09 | I32: =I26-I29 -> 23.686 | J32: =J26-J29 -> 18.804 | K32: =K26-K29 -> 21.434 | ... R32: =R26-R29 -> 32.690164
B33: % sales | D33: =D32/D20 -> 0.032631549 | E33: =E32/E20 -> 0.033212045 | F33: =F32/F20 -> 0.03436203 | G33: =G32/G20 -> 0.031591865 | H33: =H32/H20 -> 0.035929472 | I33: =I32/I20 -> 0.041354578 | J33: =J32/J20 -> 0.030761228 | K33: =K32/K20 -> 0.033070781 | ... R33: =R32/R20 -> 0.034342573
A35: X | B35: Cash flow statement
B37: Plus: D&A | D37: =CFS!D8 -> 10.08 | E37: =CFS!E8 -> 10.529 | F37: =CFS!F8 -> 10.678 | G37: =CFS!G8 -> 10.987 | H37: =CFS!H8 -> 11.152 | I37: =CFS!I8 -> 10.658 | J37: =CFS!J8 -> 10.945 | K37: =CFS!K8 -> 11.853 | ... M37: =CFS!M8 -> 14.2 | N37: =N20*N38 -> 14.928522 | O37: =O20*O38 -> 15.805599 | P37: =P20*P38 -> 16.744391 | Q37: =Q20*Q38 -> 17.775835 | R37: =R20*R38 -> 18.953335
B38: % sales | D38: =D37/D20 -> 0.020777336 | E38: =E37/E20 -> 0.021061833 | F38: =F37/F20 -> 0.020757963 | G38: =G37/G20 -> 0.020968998 | H38: =H37/H20 -> 0.019944523 | I38: =I37/I20 -> 0.018608338 | J38: =J37/J20 -> 0.017904788 | K38: =K37/K20 -> 0.018288139 | ... M38: =M37/M20 -> 0.01991138 | N38: =M38 -> 0.01991138 | O38: =N38 -> 0.01991138 | P38: =O38 -> 0.01991138 | Q38: =P38 -> 0.01991138 | R38: =Q38 -> 0.01991138
B40: Less: Capex | D40: =-CFS!B25 -> 12.174 | E40: =-CFS!C25 -> 11.477 | F40: =-CFS!D25 -> 10.619 | G40: =-CFS!E25 -> 10.051 | H40: =-CFS!F25 -> 10.344 | I40: =-CFS!G25 -> 10.705 | J40: =-CFS!H25 -> 10.264 | K40: =-CFS!I25 -> 13.106 | ... M40: =-CFS!K25 -> 20.606 | N40: =N20*N41 -> 16.397017 | O40: =O20*O41 -> 17.865168 | P40: =P20*P41 -> 19.887527 | Q40: =Q20*Q41 -> 21.724581 | R40: =R20*R41 -> 23.083856
B41: % sales | D41: =D40/D20 -> 0.02509358 | E41: =E40/E20 -> 0.022958178 | F41: =F40/F20 -> 0.020643267 | G41: =G40/G20 -> 0.019182616 | H41: =H40/H20 -> 0.018499475 | I41: =I40/I20 -> 0.018690398 | J41: =J40/J20 -> 0.016790749 | K41: =K40/K20 -> 0.020221408 | ... M41: =M40/M20 -> 0.028893937 | N41: =AVERAGE(I41:M41) -> 0.021870032 | O41: =AVERAGE(J41:N41) -> 0.022505959 | P41: =AVERAGE(K41:O41) -> 0.023649 | Q41: =AVERAGE(L41:P41) -> 0.024334519 | R41: =AVERAGE(M41:Q41) -> 0.024250689
B43: Less: Change in WC | D43: =-CFS!D14 -> -6.19 | E43: =-CFS!E14 -> -3.243 | F43: =-CFS!F14 -> -0.295 | G43: =-CFS!G14 -> 0.327 | H43: =-CFS!H14 -> -7.972 | I43: =-CFS!I14 -> 6.597 | J43: =-CFS!J14 -> -2.553 | K43: =-CFS!K14 -> -1.943 | ... M43: =-CFS!M14 -> -0.75 | N43: =N20*N44 -> 0.45401097 | O43: =O20*O44 -> -1.2517748 | P43: =P20*P44 -> -0.88892189 | Q43: =Q20*Q44 -> -0.59714499 | R43: =R20*R44 -> -0.71372039
B44: % sales | D44: =D43/D20 -> -0.012759098 | E44: =E43/E20 -> -0.0064871807 | F44: =F43/F20 -> -0.0005734781 | G44: =G43/G20 -> 0.00062408868 | H44: =H43/H20 -> -0.014257329 | I44: =I43/I20 -> 0.011518034 | J44: =J43/J20 -> -0.0041764206 | K44: =K43/K20 -> -0.0029978785 | ... M44: =M43/M20 -> -0.0010516574 | N44: =AVERAGE(I44:M44) -> 0.00060555126 | O44: =AVERAGE(J44:N44) -> -0.0015769453 | P44: =AVERAGE(K44:O44) -> -0.0010570502 | Q44: =AVERAGE(L44:P44) -> -0.00066888454 | R44: =AVERAGE(M44:Q44) -> -0.00074979723
A46: X | B46: Discounted Cash Flow
B48: EBIAT | N48: =N32 -> 26.081712 | O48: =O32 -> 26.614751 | P48: =P32 -> 28.670882 | Q48: =Q32 -> 30.618479 | R48: =R32 -> 32.690164
B49: Plus: D&A | N49: =N37 -> 14.928522 | O49: =O37 -> 15.805599 | P49: =P37 -> 16.744391 | Q49: =Q37 -> 17.775835 | R49: =R37 -> 18.953335
B50: Less: Capex | N50: =N40 -> 16.397017 | O50: =O40 -> 17.865168 | P50: =P40 -> 19.887527 | Q50: =Q40 -> 21.724581 | R50: =R40 -> 23.083856
B51: Less: Change in WC | N51: =N43 -> 0.45401097 | O51: =O43 -> -1.2517748 | P51: =P43 -> -0.88892189 | Q51: =Q43 -> -0.59714499 | R51: =R43 -> -0.71372039
B52: FCF | N52: =N48+N49-N50-N51 -> 24.159206 | O52: =O48+O49-O50-O51 -> 25.806957 | P52: =P48+P49-P50-P51 -> 26.416668 | Q52: =Q48+Q49-Q50-Q51 -> 27.266878 | R52: =R48+R49-R50-R51 -> 29.273364
B54: Discount period | N54: 1 | O54: =+N54+1 -> 2 | P54: =+O54+1 -> 3 | Q54: =+P54+1 -> 4 | R54: =+Q54+1 -> 5
B55: Discount using mid year convention | N55: 0.5 | O55: =+N55+1 -> 1.5 | P55: =+O55+1 -> 2.5 | Q55: =+P55+1 -> 3.5 | R55: =+Q55+1 -> 4.5
B56: Discounted FCF | N56: =N52/(1+$C$15)^N55 -> 23.410347 | O56: =O52/(1+$C$15)^O55 -> 23.480773 | P56: =P52/(1+$C$15)^P55 -> 22.568569 | Q56: =Q52/(1+$C$15)^Q55 -> 21.873173 | R56: =R52/(1+$C$15)^R55 -> 22.049533
B57: Terminal value (TV) | R57: =(R52*(1+$C$16))/($C$15-$C$16) -> 1529.5333
B58: Discounted TV | R58: =R57/(1+$C$15)^R55 -> 1152.0881
B59: Enterprise value | R59: =SUM(N56:R56)+R58 -> 1265.4705
B60: Plus: Cash | M60: 10.727 | R60: 10.727
B61: Less: Debt | M61: =WACC!C11 -> 34.624 | R61: =WACC!C11 -> 34.624
B62: Equity value | R62: =R59+R60-R61 -> 1241.5735
B63: Divided: Shares outstanding | M63: 7972402501
B64: Stock price | R64: =R62*10^9/M63 -> 155.73392
A66: X | B66: Sensitivity analysis
D69: TGR >>
C70: =R64 -> 155.73392 | D70: 0.02 | E70: 0.022 | F70: =+E70+0.002 -> 0.024 | G70: =+F70+0.002 -> 0.026 | H70: =+G70+0.002 -> 0.028 | I70: =+H70+0.002 -> 0.03 | J70: =+I70+0.002 -> 0.032 | K70: =+J70+0.002 -> 0.034 | L70: =+K70+0.002 -> 0.036
B71: WACC >> | C71: 0.065 | D71: 73.914332 | E71: 76.958782 | F71: 80.300251 | G71: 83.984435 | H71: 88.06691 | I71: 92.615952 | J71: 97.716394 | K71: 103.47496 | L71: 110.02781
C72: =+C71+0.25% -> 0.0675 | D72: 69.909751 | E72: 72.613216 | F72: 75.565276 | G72: 78.801872 | H72: 82.366224 | I72: 86.310774 | J72: 90.69978 | K72: 95.612847 | L72: 101.1498
C73: =+C72+0.25% -> 0.07 | D73: 66.305843 | E73: 68.720519 | F73: 71.345167 | G73: 74.20842 | H73: 77.344363 | I73: 80.793901 | J73: 84.606548 | K73: 88.842823 | L73: 93.577482
C74: =+C73+0.25% -> 0.0725 | D74: 63.045365 | E74: 65.21343 | F74: 67.560303 | G74: 70.109059 | H74: 72.886916 | I74: 75.926218 | J74: 79.265699 | K74: 82.952138 | L74: 87.042571
C75: =+C74+0.25% -> 0.075 | D75: 60.081484 | E75: 62.037378 | F75: 64.146675 | G75: 66.428159 | H75: 68.903813 | I75: 71.599524 | J75: 74.546 | K75: 77.779936 | L75: 81.345558
C76: =+C75+0.25% -> 0.0775 | D76: 57.37551 | E76: 59.147626 | F76: 61.052237 | G76: 63.104778 | H76: 65.323181 | I76: 67.728398 | J76: 70.345061 | K76: 73.202338 | L76: 76.335015
C77: =+C76+0.25% -> 0.08 | D77: 54.895203 | E77: 56.507151 | F77: 58.234238 | G77: 60.089257 | H77: 62.08697 | I77: 64.244501 | J77: 66.581825 | K77: 69.122396 | L77: 71.893927
C78: =+C77+0.25% -> 0.0825 | D78: 52.613478 | E78: 54.085046 | F78: 55.657234 | G78: 57.340728 | H78: 59.14778 | I78: 61.092513 | J78: 63.191284 | K78: 65.46315 | L78: 67.930445

Sheet WACC
B2: WACC calculation
B3: all values in B$
B4: Formula used
B5: WACC = Re*E/V + Rd*(1-t)*D/V
B6: Re = Rf + Be*(MRP)
B9: Items | C9: Value | D9: Source
B10: E | C10: =D28 -> 890.2464 | D10: Computed
B11: D | C11: 34.624 | D11: Walmart report
B12: Value (E + D) | C12: =SUM(C10:C11) -> 924.8704
B13: E/V | C13: =C10/C12 -> 0.9625634 | D13: Computed
B14: D/V | C14: =1-C13 -> 0.037436597 | D14: Computed
B16: Re | C16: =C17+C18*C19 -> 0.07147
B17: Rf | C17: 0.04471 | D17: CNBC
B18: Bequity | C18: 0.6 | D18: Stock analysis
B19: MRP | C19: 0.0446 | D19: Damodoran
B21: Rd | C21: 0.04 | D21: Walmart report
B22: 1-t | C22: =1-'DCF model'!N30 -> 0.79383056
B24: WACC | C24: =C16*C13+C21*C22*C14 -> 0.069983139
B27: E
B28: Market Capitalization | D28: =D30*D29 -> 890.2464
B29: Share price | D29: 111.84
B30: Shares outstanding | D30: 7.96

Sheet CFS
A1: Walmart Inc.
A2: WMT 931142103 2936921 NYSE Common stock
A3: Source: FactSet Fundamentals
B4: JAN '15 | C4: JAN '16 | D4: JAN '17 | E4: JAN '18 | F4: JAN '19 | G4: JAN '20 | H4: JAN '21 | I4: JAN '22 | J4: JAN '23 | K4: JAN '24 | L4: JAN '25 | M4: JAN '26
A6: Operating Activities
A7: Net Income / Starting Line | B7: 16.814 | C7: 15.08 | D7: 14.293 | E7: 10.523 | F7: 6.161 | G7: 15.201 | H7: 13.706 | I7: 13.94 | J7: 11.292 | K7: 16.27 | L7: 20.16 | M7: 22.27
A8: Depreciation, Depletion & Amortization | B8: 9.173 | C8: 9.454 | D8: 10.08 | E8: 10.529 | F8: 10.678 | G8: 10.987 | H8: 11.152 | I8: 10.658 | J8: 10.945 | K8: 11.853 | L8: 12.97 | M8: 14.2
A9: Depreciation and Depletion | B9: 9.173 | C9: 9.454 | D9: 10.08 | E9: 10.529 | F9: 10.678 | G9: 10.987 | H9: 11.152 | I9: 10.658 | J9: 10.945 | K9: 11.853 | L9: 12.97 | M9: 14.2
A10: Deferred Taxes & Investment Tax Credit | B10: -0.503 | C10: -0.672 | D10: 0.761 | E10: -0.304 | F10: -0.499 | G10: 0.32 | H10: 1.911 | I10: -0.755 | J10: 0.449 | K10: -0.175 | L10: -0.64 | M10: 2.28
A11: Deferred Taxes | B11: -0.503 | C11: -0.672 | D11: 0.761 | E11: -0.304 | F11: -0.499 | G11: 0.32 | H11: 1.911 | I11: -0.755 | J11: 0.449 | K11: -0.175 | L11: -0.64 | M11: 2.28
A12: Other Funds | B12: 0.785 | C12: 1.41 | D12: 0.206 | E12: 4.346 | F12: 11.118 | G12: -0.926 | H12: 1.333 | I12: 6.935 | J12: 3.602 | K12: 5.835 | L12: 3.77 | M12: 2.06
A13: Funds from Operations | B13: 26.269 | C13: 25.272 | D13: 25.34 | E13: 25.094 | F13: 27.458 | G13: 25.582 | H13: 28.102 | I13: 30.778 | J13: 26.288 | K13: 33.783 | L13: 36.26 | M13: 40.81
A14: Changes in Working Capital | B14: 2.295 | C14: 2.117 | D14: 6.19 | E14: 3.243 | F14: 0.295 | G14: -0.327 | H14: 7.972 | I14: -6.597 | J14: 2.553 | K14: 1.943 | L14: 0.18 | M14: 0.75
A15: Receivables | B15: -0.569 | C15: -0.019 | D15: -0.402 | E15: -1.074 | F15: -0.368 | G15: 0.154 | H15: -1.086 | I15: -1.796 | J15: 0.24 | K15: -0.797 | L15: -1.11 | M15: -1.14
A16: Inventories | B16: -1.229 | C16: -0.703 | D16: 1.021 | E16: -0.14 | F16: -1.311 | G16: -0.3 | H16: -2.395 | I16: -11.764 | J16: -0.528 | K16: 2.017 | L16: -2.76 | M16: -1.44
A17: Accounts Payable | B17: 2.678 | C17: 2.008 | D17: 3.942 | E17: 4.086 | F17: 1.831 | G17: -0.274 | H17: 6.966 | I17: 5.52 | J17: -1.425 | K17: 2.515 | L17: 3.23 | M17: 1.61
A18: Income Taxes Payable | B18: 0.166 | C18: -0.472 | D18: 0.492 | E18: -0.557 | F18: -0.04 | G18: -0.093 | H18: -0.136 | I18: 0.039 | J18: -0.127 | K18: -0.468 | L18: 0.44 | M18: 0.11
... A20: Net Operating Cash Flow | B20: 28.564 | C20: 27.389 | D20: 31.53 | E20: 28.337 | F20: 27.753 | G20: 25.255 | H20: 36.074 | I20: 24.181 | J20: 28.841 | K20: 35.726 | L20: 36.44 | M20: 41.57
B22: =B7+B8+B12+B11 -> 26.269 | C22: =C7+C8+C12+C11 -> 25.272 | D22: =D7+D8+D12+D11 -> 25.34 | E22: =E7+E8+E12+E11 -> 25.094 | F22: =F7+F8+F12+F11 -> 27.458 | G22: =G7+G8+G12+G11 -> 25.582 | H22: =H7+H8+H12+H11 -> 28.102 | I22: =I7+I8+I12+I11 -> 30.778 | ... M22: =M7+M8+M12+M11 -> 40.81
A24: Investing Activities
A25: Capital Expenditures | B25: -12.174 | C25: -11.477 | D25: -10.619 | E25: -10.051 | F25: -10.344 | G25: -10.705 | H25: -10.264 | I25: -13.106 | J25: -16.857 | K25: -20.606 | L25: -23.78 | M25: -26.64
A26: Capital Expenditures (Fixed Assets) | B26: -12.174 | C26: -11.477 | D26: -10.619 | E26: -10.051 | F26: -10.344 | G26: -10.705 | H26: -10.264 | I26: -13.106 | J26: -16.857 | K26: -20.606 | L26: -23.78 | M26: -26.64
A27: Net Assets from Acquisitions | B27: -1.844 | C27: -1.326 | D27: -2.553 | E27: -0.383 | F27: -14.656 | G27: -0.056 | H27: -0.18 | I27: -0.359 | J27: -1.567 | K27: -3.471 | L27: -1.9 | M27: -0.05
A28: Sale of Fixed Assets & Businesses | B28: 1.241 | C28: 0.881 | D28: 1.118 | E28: 1.424 | F28: 1.395 | G28: 1.154 | H28: 0.271 | I28: 8.329 | J28: 0.17 | K28: 0.385 | L28: 0.43 | M28: 0.11
A29: Purchase/Sale of Investments | B29: 0 | C29: 0 | D29: -1.901 | E29: 0 | F29: 0 | G29: 0 | H29: 0 | I29: 0 | J29: 0 | K29: 0 | L29: 4.08 | M29: 0.93
A30: Purchase of Investments | B30: 0 | C30: 0 | D30: 1.901 | E30: 0 | F30: 0 | G30: 0 | H30: 0 | I30: 0 | J30: 0 | K30: 0
A31: Sale/Maturity of Investments | B31: 0 | C31: 0 | D31: 0 | E31: 0 | F31: 0 | G31: 0 | H31: 0 | I31: 0 | J31: 0 | K31: 0
A32: Other Funds | B32: -0.192 | C32: -0.079 | D32: -0.122 | E32: -0.058 | F32: -0.431 | G32: 0.479 | H32: -1.746 | I32: -0.879 | J32: -0.295 | K32: -1.057 | L32: -0.21 | M32: -0.69
A33: Other Uses | B33: -0.192 | C33: -0.079 | D33: -0.122 | E33: -0.058 | F33: -0.431 | G33: 0 | H33: -1.848 | I33: -0.879 | J33: -0.295 | K33: -1.057
A34: Other Sources | B34: 0 | C34: 0 | D34: 0 | E34: 0 | F34: 0 | G34: 0.479 | H34: 0.102 | I34: 0 | J34: 0 | K34: 0
A35: Net Investing Cash Flow | B35: -12.969 | C35: -12.001 | D35: -14.077 | E35: -9.068 | F35: -24.036 | G35: -9.128 | H35: -11.919 | I35: -6.015 | J35: -18.549 | K35: -24.749 | L35: -21.38 | M35: -26.35
A36: Financing Activities
A37: Cash Dividends Paid | B37: -6.185 | C37: -6.294 | D37: -6.216 | E37: -6.124 | F37: -6.102 | G37: -6.048 | H37: -6.116 | I37: -6.152 | J37: -6.114 | K37: -6.14 | L37: -6.69 | M37: -7.51
A38: Common Dividends | B38: -6.185 | C38: -6.294 | D38: -6.216 | E38: -6.124 | F38: -6.102 | G38: -6.048 | H38: -6.116 | I38: -6.152 | J38: -6.114 | K38: -6.14 | L38: -6.69 | M38: -7.51
A39: Change in Capital Stock | B39: -1.015 | C39: -4.112 | D39: -8.298 | E39: -8.296 | F39: -7.41 | G39: -5.717 | H39: -2.625 | I39: -9.787 | J39: -9.92 | K39: -2.779 | L39: -4.49 | M39: -8.09
A40: Repurchase of Common & Preferred Stk. | B40: -1.015 | C40: -4.112 | D40: -8.298 | E40: -8.296 | F40: -7.41 | G40: -5.717 | H40: -2.625 | I40: -9.787 | J40: -9.92 | K40: -2.779 | L40: -4.49 | M40: -8.09
A41: Issuance/Reduction of Debt, Net | B41: -5.018 | C41: -3.158 | D41: -3.591 | E41: -1.437 | F41: 12.035 | G41: -1.071 | H41: -5.706 | I41: -5.872 | J41: 2.318 | K41: 1.262 | L41: -1.26 | M41: 4.88
A42: Change in Current Debt | B42: -6.288 | C42: 1.235 | D42: -1.673 | E42: 4.148 | F42: -0.053 | G42: -4.656 | H42: -0.324 | I42: 0.193 | J42: -0.034 | K42: 0.512 | L42: 2.21 | M42: 3.52
A43: Change in Long-Term Debt | B43: 1.27 | C43: -4.393 | D43: -1.918 | E43: -5.585 | F43: 12.088 | G43: 3.585 | H43: -5.382 | I43: -6.065 | J43: 2.352 | K43: 0.75 | L43: -3.47 | M43: 1.36
A44: Issuance of Long-Term Debt | B44: 5.174 | C44: 0.039 | D44: 0.137 | E44: 7.476 | F44: 15.872 | G44: 5.492 | H44: 0 | I44: 6.945 | J44: 5.041 | K44: 4.967 | L44: 0 | M44: 3.98
A45: Reduction in Long-Term Debt | B45: -3.904 | C45: -4.432 | D45: -2.055 | E45: -13.061 | F45: -3.784 | G45: -1.907 | H45: -5.382 | I45: -13.01 | J45: -2.689 | K45: -4.217 | L45: -3.47 | M45: -2.63
A46: Other Funds | B46: -1.009 | C46: -1.232 | D46: -0.734 | E46: -4.01 | F46: -1.06 | G46: -1.463 | H46: -1.67 | I46: -1.017 | J46: -2.496 | K46: -2.295 | L46: -2.38 | M46: -2.84
A47: Other Uses | B47: -1.009 | C47: -1.232 | D47: -0.734 | E47: -4.01 | F47: -1.06 | G47: -1.463 | H47: -1.67 | I47: -4.256 | J47: -2.562 | K47: -3.011
A48: Other Sources | I48: 3.239 | J48: 0.066 | K48: 0.716
A49: Net Financing Cash Flow | B49: -13.227 | C49: -14.796 | D49: -18.839 | E49: -19.867 | F49: -2.537 | G49: -14.299 | H49: -16.117 | I49: -22.828 | J49: -16.212 | K49: -9.952 | L49: -14.82 | M49: -13.55
A50: All Activities
A51: Exchange Rate Effect | B51: -0.514 | C51: -1.022 | D51: -0.452 | E51: 0.487 | F51: -0.438 | G51: -0.069 | H51: 0.235 | I51: -0.14 | J51: -0.073 | K51: 0.069 | L51: -0.64 | M51: 0.12
A52: Net Change in Cash | B52: 1.854 | C52: -0.43 | D52: -1.838 | E52: -0.111 | F52: 0.742 | G52: 1.759 | H52: 8.273 | I52: -4.802 | J52: -5.993 | K52: 1.094 | L52: -0.4 | M52: 1.79
A53: Free Cash Flow | B53: 16.39 | C53: 15.912 | D53: 20.911 | E53: 18.286 | F53: 17.409 | G53: 14.55 | H53: 25.81 | I53: 11.075 | J53: 11.984 | K53: 15.12 | L53: 12.66 | M53: 14.92
A54: Free Cash Flow per Share | B54: 1.684652 | C54: 1.648739 | D54: 2.239822 | E54: 2.025026 | F54: 1.970456 | G54: 1.691072 | H54: 3.021891 | I54: 1.316101 | J54: 1.461106 | K54: 1.864823 | L54: 1.57 | M54: 1.86
A55: Free Cash Flow Yield (%) | B55: 5.947237 | C55: 7.453621 | D55: 10.068135 | E55: 5.698952 | F55: 6.168606 | G55: 4.431148 | H55: 6.452903 | I55: 2.824052 | J55: 3.046724 | K55: 3.385461 | L55: 1.56 | M55: 1.6
A56: All figures in billions of U.S. Dollar except per share items.

Sheet IS
A1: Walmart Inc. (WMT)
A2: $97.67
A5: Walmart Inc.
A6: WMT 931142103 2936921 NYSE Common stock
A7: Source: FactSet Fundamentals
B8: JAN '15 | C8: JAN '16 | D8: JAN '17 | E8: JAN '18 | F8: JAN '19 | G8: JAN '20 | H8: JAN '21 | I8: JAN '22 | J8: JAN '23 | K8: JAN '24 | L8: JAN '25 | M8: JAN '26
A10: Sales | B10: 485.651 | C10: 482.13 | D10: 485.144 | E10: 499.909 | F10: 514.405 | G10: 523.964 | H10: 559.151 | I10: 572.754 | J10: 611.289 | K10: 648.125 | L10: 680.99 | M10: 713.16
A11: Cost of Goods Sold (COGS) incl. D&A | B11: 365.086 | C11: 360.984 | D11: 361.256 | E11: 373.396 | F11: 385.301 | G11: 394.605 | H11: 420.315 | I11: 429 | J11: 463.721 | K11: 490.142 | L11: 524.73 | M11: 549.6
A12: COGS excluding D&A | B12: 355.913 | C12: 351.53 | D12: 351.176 | E12: 362.867 | F12: 374.623 | G12: 383.618 | H12: 409.163 | I12: 418.342 | J12: 452.776 | K12: 478.289 | L12: 511.75 | M12: 535.4
A13: Depreciation & Amortization Expense | B13: 9.173 | C13: 9.454 | D13: 10.08 | E13: 10.529 | F13: 10.678 | G13: 10.987 | H13: 11.152 | I13: 10.658 | J13: 10.945 | K13: 11.853 | L13: 12.97 | M13: 14.2
A14: Depreciation | B14: 9.173 | C14: 9.454 | D14: 10.08 | E14: 10.529 | F14: 10.678 | G14: 10.987 | H14: 11.152 | I14: 10.658 | J14: 10.945 | K14: 11.853 | L14: 12.97 | M14: 14.2
A15: Gross Income | B15: 120.565 | C15: 121.146 | D15: 123.888 | E15: 126.513 | F15: 129.104 | G15: 129.359 | H15: 138.836 | I15: 143.754 | J15: 147.568 | K15: 157.983 | L15: 162.79 | M15: 171.02
A16: SG&A Expense | B16: 93.418 | C16: 97.041 | D16: 101.853 | E16: 105.31 | F16: 107.147 | G16: 107.891 | H16: 111.888 | I16: 115.312 | J16: 123.04 | K16: 130.971 | L16: 139.88 | M16: 147.94
A17: Other SG&A | B17: 93.418 | C17: 97.041 | D17: 101.853 | E17: 105.31 | F17: 107.147 | G17: 107.891 | H17: 111.888 | I17: 115.312 | J17: 123.04 | K17: 130.971 | L17: 139.88 | M17: 147.94
A18: EBIT (Operating Income) | B18: 27.147 | C18: 24.105 | D18: 22.035 | E18: 21.203 | F18: 21.957 | G18: 21.468 | H18: 26.948 | I18: 28.442 | J18: 24.528 | K18: 27.012 | L18: 29.35 | M18: 29.83
A19: Nonoperating Income - Net | B19: 0.139 | C19: 0.096 | D19: 0.872 | E19: 0.587 | F19: 0.266 | G19: 0.189 | H19: -8.179 | I19: -0.275 | J19: 0.254 | K19: 0.546 | L19: =SUM(L20:L21) -> 1.27 | M19: =SUM(M20:M21) -> -1.71
A20: Nonoperating Interest Income | B20: 0.113 | C20: 0.081 | D20: 0.1 | E20: 0.152 | F20: 0.217 | G20: 0.189 | H20: 0.121 | I20: 0.158 | J20: 0.254 | K20: 0.546 | L20: 0.48 | M20: 0.37
A21: Other Income (Expense) | B21: 0.026 | C21: 0.015 | D21: 0.772 | E21: 0.435 | F21: 0.049 | G21: 0 | H21: -8.3 | I21: -0.433 | J21: 0 | K21: 0 | L21: 0.79 | M21: -2.08
A22: Interest Expense | B22: 2.487 | C22: 2.563 | D22: 2.41 | E22: 2.331 | F22: 2.395 | G22: 2.599 | H22: 2.315 | I22: 1.994 | J22: 2.128 | K22: 2.683 | L22: 2.25 | M22: 2.43
A23: Gross Interest Expense | B23: 2.546 | C23: 2.602 | D23: 2.446 | E23: 2.348 | F23: 2.395 | G23: 2.599 | H23: 2.315 | I23: 1.994 | J23: 2.128 | K23: 2.683 | L23: 2.73 | M23: 2.8
A24: Interest Capitalized | B24: 0.059 | C24: 0.039 | D24: 0.036 | E24: 0.017 | F24: 0 | G24: 0 | H24: 0 | I24: 0 | J24: 0 | K24: 0 | L24: 0 | M24: 0
A25: Unusual Expense - Net | B25: 0 | C25: 0 | D25: 0 | E25: 4.336 | F25: 8.368 | G25: -1.058 | H25: -4.11 | I25: 7.477 | J25: 5.638 | K25: 3.027 | L25: 0 | M25: 0
A26: Impairments | G26: 0.9 | H26: 0 | I26: 0 | L26: 0 | M26: 0
A27: Other Intangibles | B27: 0 | C27: 0 | D27: 0 | E27: 0 | F27: 0 | G27: 0.9 | H27: 0 | I27: 0 | J27: 0 | K27: 0 | L27: 0 | M27: 0
A28: Restructuring Expense | B28: 0 | C28: 0 | D28: 0 | E28: 1.2 | F28: 0 | G28: 0 | H28: 0.4 | I28: 0 | J28: 0.8 | K28: 0 | L28: 0 | M28: 0
A29: Legal Claim Expense | J29: 3.3
A30: Unrealized Valuation Gain/Loss | F30: -8.368 | G30: 1.958 | H30: 8.51 | I30: -2.567 | J30: -1.538 | K30: -3.027
A31: Investments | H31: 8.51 | I31: -2.567 | J31: -1.538 | K31: -3.027
A32: Hedges/Derivatives | F32: -8.368 | G32: 1.958
A33: Excpl Chrgs - Others | E33: 3.136 | F33: 0 | G33: 0 | H33: 4 | I33: 4.91 | K33: 0
A34: Restructuring of Debt | E34: 3.136 | F34: 0 | G34: 0 | I34: 2.41 | K34: 0
A35: Other Unusual Expense | H35: 4 | I35: 2.5
A36: Pretax Income | B36: 24.799 | C36: 21.638 | D36: 20.497 | E36: 15.123 | F36: 11.46 | G36: 20.116 | H36: 20.564 | I36: 18.696 | J36: 17.016 | K36: 21.848 | L36: 26.31 | M36: 29.47
A37: Income Taxes | B37: 7.985 | C37: 6.558 | D37: 6.204 | E37: 4.6 | F37: 4.281 | G37: 4.915 | H37: 6.858 | I37: 4.756 | J37: 5.724 | K37: 5.578 | L37: 6.15 | M37: 7.2
A38: Income Taxes - Current Domestic | B38: 6.975 | C38: 6.184 | D38: 3.949 | E38: 3.403 | F38: 3.256 | G38: 3.381 | H38: 3.733 | I38: 3.962 | J38: 2.64 | K38: 3.977
A39: Income Taxes - Current Foreign | B39: 1.529 | C39: 1.4 | D39: 1.51 | E39: 1.377 | F39: 1.495 | G39: 1.205 | H39: 1.127 | I39: 1.553 | J39: 2.654 | K39: 1.772
A40: Income Taxes - Deferred Domestic | B40: -0.442 | C40: -0.81 | D40: 1.105 | E40: -0.034 | F40: -0.377 | G40: 0.698 | H40: 2.339 | I40: -0.63 | J40: 0.727 | K40: -0.297
A41: Income Taxes - Deferred Foreign | B41: -0.077 | C41: -0.216 | D41: -0.36 | E41: -0.146 | F41: -0.093 | G41: -0.369 | H41: -0.341 | I41: -0.129 | J41: -0.297 | K41: 0.126
A42: Consolidated Net Income | B42: 16.814 | C42: 15.08 | D42: 14.293 | E42: 10.523 | F42: 7.179 | G42: 15.201 | H42: 13.706 | I42: 13.94 | J42: 11.292 | K42: 16.27 | L42: 20.16 | M42: 22.27
A43: Minority Interest | B43: 0.632 | C43: 0.386 | D43: 0.65 | E43: 0.661 | F43: 0.509 | G43: 0.32 | H43: 0.196 | I43: 0.267 | J43: -0.388 | K43: 0.759 | L43: 0.72 | M43: 0.38
A44: Net Income | B44: 16.182 | C44: 14.694 | D44: 13.643 | E44: 9.862 | F44: 6.67 | G44: 14.881 | H44: 13.51 | I44: 13.673 | J44: 11.68 | K44: 15.511 | L44: 19.44 | M44: 21.89
A45: Discontinued Operations | B45: 0.181 | C45: 0 | D45: 0 | E45: 0 | F45: 0 | G45: 0 | H45: 0 | I45: 0 | J45: 0 | K45: 0 | L45: 0 | M45: 0
A46: Net Income available to Common | B46: 16.363 | C46: 14.694 | D46: 13.643 | E46: 9.862 | F46: 6.67 | G46: 14.881 | H46: 13.51 | I46: 13.673 | J46: 11.68 | K46: 15.511 | L46: 19.44 | M46: 21.89
A47: Per Share
A48: EPS (recurring) | B48: 1.681877 | C48: 1.522535 | D48: 1.461331 | E48: 1.42826 | F48: 1.41795 | G48: 1.643466 | H48: 1.244935 | I48: 2.246807 | J48: 1.905216 | K48: 2.174381
A49: EPS (basic) | B49: 1.69 | C49: 1.5267 | D49: 1.4667 | E49: 1.0967 | F49: 0.76 | G49: 1.7405 | H49: 1.5907 | I49: 1.6324 | J49: 1.4293 | K49: 1.9204 | L49: 2.42 | M49: 2.74
A50: Basic Shares Outstanding (M) | B50: 9690.01 | C50: 9621.0099 | D50: 9303.0096 | E50: 8985.0093 | F50: 8787.0091 | G50: 8550.0088 | H50: 8493.0087 | I50: 8376.0086 | J50: 8172.0084 | K50: 8077.0083 | L50: 8041 | M50: 7983
A51: Total Shares Outstanding (M) | B51: 9684.01 | C51: 9486.0098 | D51: 9144.0094 | E51: 8856.0091 | F51: 8634.0089 | G51: 8497.4874 | H51: 8463.0087 | I51: 8283.0085 | J51: 8079.0083 | K51: 8054.0083 | L51: 8016.85 | M51: 7972.4
A52: EPS (diluted) | B52: 1.6833 | C52: 1.5233 | D52: 1.46 | E52: 1.0933 | F52: 0.7533 | G52: 1.7295 | H52: 1.5818 | I52: 1.6248 | J52: 1.424 | K52: 1.913 | L52: 2.41 | M52: 2.73
A53: Diluted Shares Outstanding (M) | B53: 9729.01 | C53: 9651.0099 | D53: 9336.0096 | E53: 9030.0093 | F53: 8835.0091 | G53: 8604.0089 | H53: 8541.0088 | I53: 8415.0087 | J53: 8202.0084 | K53: 8108.0084 | L53: 8081 | M53: 8022
A54: Total Shares Outstanding (M) | B54: 9684.01 | C54: 9486.0098 | D54: 9144.0094 | E54: 8856.0091 | F54: 8634.0089 | G54: 8497.4874 | H54: 8463.0087 | I54: 8283.0085 | J54: 8079.0083 | K54: 8054.0083 | L54: 8040.5 | M54: 8080.51
A55: Earnings Persistence | B55: 92.66 | C55: 94.604 | D55: 90.338 | E55: 89.626 | F55: 88.924 | G55: 87.993 | H55: 85.898 | I55: 92.57 | J55: 96.198 | K55: 89.472
A56: Dividends per Share | B56: 0.64 | C56: 0.65333 | D56: 0.66667 | E56: 0.68 | F56: 0.69333 | G56: 0.70667 | H56: 0.72 | I56: 0.73333 | J56: 0.74667 | K56: 0.76 | L56: 0.83 | M56: 0.94
A57: Payout Ratio | B57: 38.020555 | C57: 42.889122 | D57: 45.662329 | E57: 62.197018 | F57: 92.039028 | G57: 40.859786 | H57: 45.517765 | I57: 45.133555 | J57: 52.434691 | K57: 39.728176
A58: EBITDA
A59: EBITDA | B59: 36.32 | C59: 33.559 | D59: 32.115 | E59: 31.732 | F59: 32.635 | G59: 32.455 | H59: 38.1 | I59: 39.1 | J59: 35.473 | K59: 38.865 | L59: 42.32 | M59: 44.03
A60: EBIT | B60: 27.147 | C60: 24.105 | D60: 22.035 | E60: 21.203 | F60: 21.957 | G60: 21.468 | H60: 26.948 | I60: 28.442 | J60: 24.528 | K60: 27.012 | L60: 29.35 | M60: 29.83
A61: Depreciation & Amortization Expense | B61: 9.173 | C61: 9.454 | D61: 10.08 | E61: 10.529 | F61: 10.678 | G61: 10.987 | H61: 11.152 | I61: 10.658 | J61: 10.945 | K61: 11.853 | L61: 12.97 | M61: 14.2
A62: All figures in billions of U.S. Dollar except per share and labeled items.
